herb/__init__.py
herb/metadata.py
herb/models.py
herb/traversal.py
herb-0.1.0.dist-info/WHEEL
herb-0.1.0.dist-info/METADATA
herb-0.1.0.dist-info/RECORD
