Metadata-Version: 2.1
Name: herb
Version: 0.1.0
Summary: Effortless Offline Backups
Author: eukaryote
Author-email: eukaryote31@gmail.com
Requires-Python: >=3.6,<4.0
Classifier: Programming Language :: Python :: 3
Classifier: Programming Language :: Python :: 3.6
Classifier: Programming Language :: Python :: 3.7
Requires-Dist: more_itertools (>=7.1,<8.0)
Requires-Dist: sqlalchemy (>=1.3,<2.0)
